asreviewcontrib/covid19/__init__.py
asreviewcontrib/covid19/_version.py
asreviewcontrib/covid19/datasets.py
asreview_covid19-0.9.4.dist-info/LICENSE
asreview_covid19-0.9.4.dist-info/METADATA
asreview_covid19-0.9.4.dist-info/WHEEL
asreview_covid19-0.9.4.dist-info/entry_points.txt
asreview_covid19-0.9.4.dist-info/top_level.txt
asreview_covid19-0.9.4.dist-info/RECORD
