Metadata-Version: 2.1
Name: asreview-covid19
Version: 0.9.4
Summary: Covid-19 related datasets for ASReview
Home-page: https://github.com/asreview/asreview-covid19
Author: Utrecht University
Author-email: asreview@uu.nl
License: UNKNOWN
Project-URL: Bug Reports, https://github.com/asreview/asreview-covid19/issues
Project-URL: Source, https://github.com/asreview/asreview-covid19
Keywords: asreview covid19
Platform: UNKNOWN
Classifier: Development Status :: 7 - Inactive
Classifier: License :: OSI Approved :: Apache Software License
Classifier: Programming Language :: Python :: 3.5
Classifier: Programming Language :: Python :: 3.6
Classifier: Programming Language :: Python :: 3.7
License-File: LICENSE
Requires-Dist: asreview (<1.0)
Provides-Extra: all
Requires-Dist: asreview-statistics ; extra == 'all'
Provides-Extra: config-create
Requires-Dist: asreview-statistics ; extra == 'config-create'
